setup.py
docs/README.md
docs/src/PLACE_YOUR_DOCS_HERE
docs/src/_config.yml
docs/src/_toc.yml
docs/src/intro.md
docs/src/logo.png
docs/src/references.bib
docs/src/_images/favicon.ico
docs/src/_static/ADD_CSS_AND_JS_FILES_HERE
docs/src/api/dtproject/api.rst
docs/src/dtproject/get-started/index.md
docs/src/dtproject/introduction/index.md
docs/src/dtproject/the-dtproject-directory/index.md
html/HTML_DOCS_WILL_BE_GENERATED_HERE
notebooks/.gitignore
notebooks/00-hello.ipynb
notebooks/Makefile
notebooks/README.md
notebooks/custom.css
notebooks/execute.sh
notebooks-extra/00-private.ipynb
notebooks-extra/README.md
pdf/PDF_WILL_BE_GENERATED_HERE
src/dtproject/__init__.py
src/dtproject/configurations.py
src/dtproject/constants.py
src/dtproject/dtproject.py
src/dtproject/exceptions.py
src/dtproject/recipe.py
src/dtproject/types.py
src/dtproject.egg-info/PKG-INFO
src/dtproject.egg-info/SOURCES.txt
src/dtproject.egg-info/dependency_links.txt
src/dtproject.egg-info/requires.txt
src/dtproject.egg-info/top_level.txt
src/dtproject/assets/schemas/base.yaml.json
src/dtproject/assets/schemas/containers.yaml.json
src/dtproject/assets/schemas/devcontainers.yaml.json
src/dtproject/assets/schemas/distro.yaml.json
src/dtproject/assets/schemas/format.yaml.json
src/dtproject/assets/schemas/hooks.yaml.json
src/dtproject/assets/schemas/recipes.yaml.json
src/dtproject/assets/schemas/self.yaml.json
src/dtproject/assets/schemas/template.yaml.json
src/dtproject/utils/__init__.py
src/dtproject/utils/docker.py
src/dtproject/utils/misc.py