Metadata-Version: 2.1
Name: dtproject
Version: 1.0.12
Summary: UNKNOWN
Home-page: http://github.com/duckietown/lib-dtproject
Author: Andrea F. Daniele
Author-email: afdaniele@duckietown.com
License: UNKNOWN
Platform: UNKNOWN
